[
  {
    "gambar": "https://imgur.com/apfUsWE.jpg",
    "link": "https://shope.ee/LKc4TtePw?share_channel_code=1"
  },
  {
    "gambar": "https://imgur.com/GnzqSjy.jpg",
    "link": "https://shope.ee/1q9PDus2XB?share_channel_code=1"
  },
  {
    "gambar": "https://imgur.com/qLOLfTf.jpg",
    "link": "https://shope.ee/9pBgdk1jcW?share_channel_code=1"
  },
  {
    "gambar": "https://imgur.com/96WVJIH.jpg",
    "link": "https://shope.ee/8KMrbyMlEw?share_channel_code=1"
  },
  {
    "gambar": "https://imgur.com/TRHebYZ.jpg",
    "link": "https://shope.ee/fxPReAdmr?share_channel_code=1"
  },
  {
    "gambar": "https://imgur.com/SVy6CSq.jpg",
    "link": "https://shope.ee/4AXHMWd8TL?share_channel_code=1"
  },
  {
    "gambar": "https://imgur.com/qEw3CzQ.jpg",
    "link": "https://shope.ee/5V2eKd4eMy?share_channel_code=1"
  }
]